MANIFEST.in
README.rst
setup.cfg
setup.py
src/kith/__init__.py
src/kith.egg-info/PKG-INFO
src/kith.egg-info/SOURCES.txt
src/kith.egg-info/dependency_links.txt
src/kith.egg-info/top_level.txt