Metadata-Version: 1.0
Name: kith
Version: 0.1.0
Summary: A little relational algebra engine
Home-page: http://github.com/inglesp/kith
Author: Peter Inglesby
Author-email: peter.inglesby@gmail.com
License: License :: OSI Approved :: MIT License
Platform: UNKNOWN
